MANIFEST.in
README.rst
setup.py
ni2c/__init__.py
ni2c.egg-info/PKG-INFO
ni2c.egg-info/SOURCES.txt
ni2c.egg-info/dependency_links.txt
ni2c.egg-info/not-zip-safe
ni2c.egg-info/top_level.txt