Metadata-Version: 1.0
Name: ni2c
Version: 0.1
Summary: Universal nixie i2c module driver for the Omega2 platform
Home-page: https://github.com/danielkummer/ni2c
Author: Daniel Kummer
Author-email: daniel.kummer@gmail.com
License: CC BY-NC-SA 4.0
Platform: UNKNOWN
